mod/__init__.py
mod/example.py
try_packaging2_mod1/__init__.py
try_packaging2_mod1/example.py
try_packaging2_module/__init__.py
try_packaging2_module/add.py
try_packaging2_module/demo.py
try_packaging2_module/subtract.py
try_packaging2_module/extras/__init__.py
try_packaging2_module/extras/divide.py
try_packaging2_module/extras/multiply.py
verysimplemodule/__init__.py
verysimplemodule/add.py
verysimplemodule/subtract.py
verysimplemodule/extras/__init__.py
verysimplemodule/extras/divide.py
verysimplemodule/extras/multiply.py
try_packaging2_module-0.0.7.dist-info/METADATA
try_packaging2_module-0.0.7.dist-info/WHEEL
try_packaging2_module-0.0.7.dist-info/top_level.txt
try_packaging2_module-0.0.7.dist-info/RECORD
